pulumi_lagoon/__init__.py
pulumi_lagoon/client.py
pulumi_lagoon/config.py
pulumi_lagoon/deploytarget.py
pulumi_lagoon/deploytarget_config.py
pulumi_lagoon/environment.py
pulumi_lagoon/exceptions.py
pulumi_lagoon/import_utils.py
pulumi_lagoon/project.py
pulumi_lagoon/py.typed
pulumi_lagoon/validators.py
pulumi_lagoon/variable.py
pulumi_lagoon-0.1.0.dist-info/licenses/LICENSE
pulumi_lagoon-0.1.0.dist-info/METADATA
pulumi_lagoon-0.1.0.dist-info/WHEEL
pulumi_lagoon-0.1.0.dist-info/top_level.txt
pulumi_lagoon-0.1.0.dist-info/RECORD
