Metadata-Version: 2.4
Name: pulumi-lagoon
Version: 0.1.0
Summary: A Pulumi dynamic provider for managing Lagoon resources
Home-page: https://github.com/tag1consulting/pulumi-lagoon-provider
Author: Greg Chaix
Author-email: Greg Chaix <greg@tag1consulting.com>
Maintainer-email: Tag1 Consulting <info@tag1consulting.com>
License: Apache-2.0
Project-URL: Homepage, https://github.com/tag1consulting/pulumi-lagoon-provider
Project-URL: Documentation, https://github.com/tag1consulting/pulumi-lagoon-provider#readme
Project-URL: Repository, https://github.com/tag1consulting/pulumi-lagoon-provider.git
Project-URL: Issues, https://github.com/tag1consulting/pulumi-lagoon-provider/issues
Project-URL: Changelog, https://github.com/tag1consulting/pulumi-lagoon-provider/blob/main/RELEASE_NOTES.md
Keywords: pulumi,lagoon,infrastructure-as-code,iac,devops,kubernetes,amazee
Classifier: Development Status :: 3 - Alpha
Classifier: Intended Audience :: Developers
Classifier: Intended Audience :: System Administrators
Classifier: Topic :: Software Development :: Libraries :: Python Modules
Classifier: Topic :: System :: Systems Administration
Classifier: License :: OSI Approved :: Apache Software License
Classifier: Programming Language :: Python :: 3
Classifier: Programming Language :: Python :: 3.8
Classifier: Programming Language :: Python :: 3.9
Classifier: Programming Language :: Python :: 3.10
Classifier: Programming Language :: Python :: 3.11
Classifier: Programming Language :: Python :: 3.12
Classifier: Operating System :: OS Independent
Requires-Python: >=3.8
License-File: LICENSE
Requires-Dist: pulumi<4.0.0,>=3.0.0
Requires-Dist: requests<3.0.0,>=2.28.0
Requires-Dist: PyJWT>=2.8.0
Provides-Extra: dev
Requires-Dist: pytest>=7.0.0; extra == "dev"
Requires-Dist: pytest-cov>=4.0.0; extra == "dev"
Requires-Dist: pytest-mock>=3.10.0; extra == "dev"
Requires-Dist: ruff>=0.1.0; extra == "dev"
Requires-Dist: mypy>=1.0.0; extra == "dev"
Requires-Dist: types-requests>=2.28.0; extra == "dev"
Requires-Dist: build>=1.0.0; extra == "dev"
Requires-Dist: twine>=4.0.0; extra == "dev"
Dynamic: author
Dynamic: home-page
Dynamic: license-file
Dynamic: requires-python
